sports31/__init__.py
sports31/config_func.py
sports31/logging_config.py
sports31/oneclick.py
sports31/bmi/bmi.py
sports31/bmi/bmi_cli.py
sports31/crawl/__init__.py
sports31/crawl/cli.py
sports31/crawl/coros_type.py
sports31/crawl/crawler.py
sports31/crawl/login.py
sports31-0.0.5.dist-info/METADATA
sports31-0.0.5.dist-info/WHEEL
sports31-0.0.5.dist-info/entry_points.txt
sports31-0.0.5.dist-info/top_level.txt
sports31-0.0.5.dist-info/RECORD
