Metadata-Version: 2.4
Name: sports31
Version: 0.0.5
Summary: process data
Author-email: Tom <huqh1101@gmail.com>
Maintainer-email: Tom <huqh1101@gmail.com>
License: MIT License
Keywords: sports data,coros
Classifier: Development Status :: 3 - Alpha
Classifier: Intended Audience :: Developers
Classifier: Topic :: Software Development
Classifier: License :: OSI Approved :: MIT License
Classifier: Programming Language :: Python :: 3
Classifier: Programming Language :: Python :: 3.10
Requires-Python: >=3.6
Requires-Dist: click==8.1.8
Requires-Dist: tenacity==9.0.0
Requires-Dist: requests==2.32.3
Requires-Dist: PyYAML==6.0.2
Requires-Dist: tqdm==4.67.1
Requires-Dist: timer1101==0.0.3
Requires-Dist: coloredlogs==15.0.1
Requires-Dist: verboselogs==1.7
Requires-Dist: pandas==2.2.3
Provides-Extra: test
Requires-Dist: unittest; extra == "test"
